LICENSE.txt
MANIFEST.in
README.md
setup.py
focusDB.egg-info/PKG-INFO
focusDB.egg-info/SOURCES.txt
focusDB.egg-info/dependency_links.txt
focusDB.egg-info/entry_points.txt
focusDB.egg-info/not-zip-safe
focusDB.egg-info/requires.txt
focusDB.egg-info/top_level.txt
py16db/FocusDBData.py
py16db/__init__.py
py16db/_version.py
py16db/align_and_trim_focusdb.py
py16db/calculate_shannon_entropy.py
py16db/combine_focusdb_and_silva.py
py16db/generator.py
py16db/make_silva_style_db_from_contigs.py
py16db/prefetch.py
py16db/rebuild_db.py
py16db/run_focusDB.py
py16db/shared_methods.py
py16db/test_FocusDBData.py
py16db/test_alignment.py
py16db/test_check_rDNA_num.py
py16db/test_focusDB.py
py16db/test_parse_fastq_dir.py
py16db/test_run_kraken2.py
py16db/test_shared_methods.py
py16db/test_status_file.py