Metadata-Version: 1.0
Name: focusDB
Version: 0.3.74
Summary: Draft genome reassembly using riboSeed, for the construction of high resolution 16S databases
Home-page: https://github.com/FEMLab/focusdb
Author: Ben Nolan,Nick Waters
Author-email: N.BEN1@nuigalway.ie, nickp60@gmail.com
License: MIT
Keywords: bioinformatics,assembly,16s,database
Platform: UNKNOWN
